herr_ober-0.2.0.dist-info/licenses/LICENSE
ober/__init__.py
ober/cli.py
ober/config.py
ober/system.py
ober/commands/__init__.py
ober/commands/bootstrap.py
ober/commands/config.py
ober/commands/doctor.py
ober/commands/health.py
ober/commands/logs.py
ober/commands/service.py
ober/commands/status.py
ober/commands/sync.py
ober/commands/test.py
ober/commands/uninstall.py
ober/commands/upgrade.py
herr_ober-0.2.0.dist-info/METADATA
herr_ober-0.2.0.dist-info/WHEEL
herr_ober-0.2.0.dist-info/entry_points.txt
herr_ober-0.2.0.dist-info/top_level.txt
herr_ober-0.2.0.dist-info/RECORD
