Metadata-Version: 2.4
Name: herr-ober
Version: 0.2.0
Summary: High-performance S3 ingress controller for Ceph RGW clusters using HAProxy and ExaBGP
Author-email: Dirk Petersen <dirk@petersen.org>
License: MIT
Project-URL: Homepage, https://github.com/dirkpetersen/ober
Project-URL: Documentation, https://github.com/dirkpetersen/ober#readme
Project-URL: Repository, https://github.com/dirkpetersen/ober.git
Project-URL: Issues, https://github.com/dirkpetersen/ober/issues
Keywords: s3,ceph,rgw,haproxy,bgp,ecmp,load-balancer,ingress
Classifier: Development Status :: 4 - Beta
Classifier: Environment :: Console
Classifier: Intended Audience :: System Administrators
Classifier: License :: OSI Approved :: MIT License
Classifier: Operating System :: POSIX :: Linux
Classifier: Programming Language :: Python :: 3
Classifier: Programming Language :: Python :: 3.12
Classifier: Programming Language :: Python :: 3.13
Classifier: Topic :: Internet :: Proxy Servers
Classifier: Topic :: System :: Networking
Requires-Python: >=3.12
License-File: LICENSE
Requires-Dist: click>=8.1.0
Requires-Dist: inquirer>=3.1.0
Requires-Dist: rich>=13.0.0
Requires-Dist: hostlist>=1.4.0
Requires-Dist: requests>=2.31.0
Requires-Dist: pyyaml>=6.0
Requires-Dist: watchdog>=3.0.0
Provides-Extra: route53
Requires-Dist: boto3>=1.34.0; extra == "route53"
Provides-Extra: dev
Requires-Dist: pytest>=7.4.0; extra == "dev"
Requires-Dist: pytest-cov>=4.1.0; extra == "dev"
Requires-Dist: moto[server]>=4.2.0; extra == "dev"
Requires-Dist: boto3>=1.34.0; extra == "dev"
Requires-Dist: ruff>=0.1.0; extra == "dev"
Requires-Dist: mypy>=1.5.0; extra == "dev"
Requires-Dist: types-requests>=2.31.0; extra == "dev"
Requires-Dist: types-PyYAML>=6.0.0; extra == "dev"
Dynamic: license-file
